ZidanBiji/README.md
ZidanBiji/__init__.py
ZidanBiji/__main__.py
ZidanBiji/file.epub
ZidanBiji/index.html
ZidanBiji/css/__init__.py
ZidanBiji/css/annotations.css
ZidanBiji/css/main.css
ZidanBiji/css/normalize.css
ZidanBiji/css/popup.css
ZidanBiji/font/__init__.py
ZidanBiji/font/fontello.eot
ZidanBiji/font/fontello.svg
ZidanBiji/font/fontello.ttf
ZidanBiji/font/fontello.woff
ZidanBiji/img/__init__.py
ZidanBiji/img/annotator-glyph-sprite.png
ZidanBiji/img/annotator-icon-sprite.png
ZidanBiji/img/apple-touch-icon.png
ZidanBiji/img/cancelfullscreen.png
ZidanBiji/img/close.png
ZidanBiji/img/fullscreen.png
ZidanBiji/img/loader.gif
ZidanBiji/img/menu-icon.png
ZidanBiji/img/save.png
ZidanBiji/img/saved.png
ZidanBiji/img/settings-s.png
ZidanBiji/img/settings.png
ZidanBiji/img/star.png
ZidanBiji/js/__init__.py
ZidanBiji/js/epub.js
ZidanBiji/js/epub.min.js
ZidanBiji/js/epub.min.map
ZidanBiji/js/hooks.min.js
ZidanBiji/js/hooks.min.map
ZidanBiji/js/reader.js
ZidanBiji/js/reader.js.map
ZidanBiji/js/reader.min.js
ZidanBiji/js/reader.min.map
ZidanBiji/js/hooks/__init__.py
ZidanBiji/js/hooks/extensions/__init__.py
ZidanBiji/js/hooks/extensions/highlight.js
ZidanBiji/js/libs/__init__.py
ZidanBiji/js/libs/jquery.min.js
ZidanBiji/js/libs/localforage.min.js
ZidanBiji/js/libs/screenfull.js
ZidanBiji/js/libs/screenfull.min.js
ZidanBiji/js/libs/zip.min.js
ZidanBiji/js/plugins/__init__.py
ZidanBiji/js/plugins/hypothesis.js
ZidanBiji/js/plugins/search.js
zidan_biji-2022.10.15.0.dist-info/METADATA
zidan_biji-2022.10.15.0.dist-info/WHEEL
zidan_biji-2022.10.15.0.dist-info/entry_points.txt
zidan_biji-2022.10.15.0.dist-info/top_level.txt
zidan_biji-2022.10.15.0.dist-info/RECORD
